uffpy.cpython-311-i386-linux-musl.so
uffpy-0.0.1.dist-info/top_level.txt
uffpy-0.0.1.dist-info/LICENSE.txt
uffpy-0.0.1.dist-info/RECORD
uffpy-0.0.1.dist-info/METADATA
uffpy-0.0.1.dist-info/WHEEL
uffpy.libs/libgcc_s-8b50eaaa.so.1
uffpy.libs/libstdc++-8baf04f9.so.6.0.28
